RChaM.v
`timescale  1ns /1ps

module circuit_behavior(F,A,B,C,D);
    input A,B,C,D;
    output reg F; 

    always @(A,B,C,D)
    begin 
        case({A,B,C,D})
            4'd0, 4'd1, 4'd2, 4'd8, 4'd10, 4'd12, 4'd14:
                F = 1'b0;
            default:
                F = 1'b1;
        endcase
    end 
endmodule

RChaM_tb.v
`timescale 1ns / 1ps 


module behavior_model_tb();
    reg[3:0] t_input; 
    wire t_F;
    integer i; 

    circuit_behavior dut (t_F, t_input[3], t_input[2], t_input[1], t_input[0]);

    initial begin
        t_input = 4'b0000;

        for(i = 1; i<16; i=i+1)
            begin 
                #30 t_input = i;
            end 
    end

    initial begin
         $display("Written by Max Benedict Chavez");
         $monitor("time = %0d ", $time, "A = %b B = %b C = %b D = %b output_F = %b",  t_input[3], t_input[2], t_input[1], t_input[0], t_F);
         $dumpfile("RChaM.vcd");
         $dumpvars();
    end

endmodule

RChaM.vcd
$date
	Sat Feb 14 20:47:35 2026
$end
$version
	Icarus Verilog
$end
$timescale
	1ps
$end
$scope module behavior_model_tb $end
$var wire 1 ! t_F $end
$var reg 4 " t_input [3:0] $end
$var integer 32 # i [31:0] $end
$scope module dut $end
$var wire 1 $ A $end
$var wire 1 % B $end
$var wire 1 & C $end
$var wire 1 ' D $end
$var reg 1 ! F $end
$upscope $end
$upscope $end
$enddefinitions $end
$comment Show the parameter values. $end
$dumpall
$end
#0
$dumpvars
0'
0&
0%
0$
b1 #
b0 "
0!
$end
#30000
1'
b10 #
b1 "
#60000
1&
0'
b11 #
b10 "
#90000
1!
1'
b100 #
b11 "
#120000
1%
0&
0'
b101 #
b100 "
#150000
1'
b110 #
b101 "
#180000
1&
0'
b111 #
b110 "
#210000
1'
b1000 #
b111 "
#240000
0!
1$
0%
0&
0'
b1001 #
b1000 "
#270000
1!
1'
b1010 #
b1001 "
#300000
0!
1&
0'
b1011 #
b1010 "
#330000
1!
1'
b1100 #
b1011 "
#360000
0!
1%
0&
0'
b1101 #
b1100 "
#390000
1!
1'
b1110 #
b1101 "
#420000
0!
1&
0'
b1111 #
b1110 "
#450000
1!
1'
b10000 #
b1111 "
